coopgantt/__init__.py
coopgantt/build_and_schedule_gantt.py
coopgantt/enums.py
coopgantt/exceptions.py
coopgantt/gantt.py
coopgantt/cli/__init__.py
coopgantt/cli/run_cli.py
coopgantt/cli/user_operations.py
coopgantt/rendering/__init__.py
coopgantt/rendering/build_html.py
coopgantt/rendering/coloring.py
coopgantt/rendering/svg_renderer.py
coopgantt/rendering/assets/myScripts.js
coopgantt/rendering/assets/styles.css
coopgantt-0.15.dist-info/LICENSE
coopgantt-0.15.dist-info/METADATA
coopgantt-0.15.dist-info/WHEEL
coopgantt-0.15.dist-info/top_level.txt
coopgantt-0.15.dist-info/RECORD
