Metadata-Version: 2.1
Name: coopgantt
Version: 0.15
Summary: Used for scheduling tasks based on various input configuration criteria
Home-page: https://github.com/tylertjburns/coopgantt
Author: tburns
Author-email: tyler.tj.burns@gmail.com
License: MIT
Platform: UNKNOWN
Classifier: Development Status :: 3 - Alpha
Classifier: License :: OSI Approved :: MIT License
Classifier: Programming Language :: Python
Classifier: Programming Language :: Python :: 3.5
Classifier: Programming Language :: Python :: 3.6
Classifier: Topic :: Software Development :: Libraries
Classifier: Topic :: Software Development :: Libraries :: Python Modules
Classifier: Intended Audience :: Developers
Requires-Python: >3.5
Requires-Dist: coopbugger (==0.2)
Requires-Dist: cooptools (==0.11)
Requires-Dist: coopui (==0.14)
Requires-Dist: numpy (==1.19.4)
Requires-Dist: pandas (==1.2.4)
Requires-Dist: python-dateutil (==2.8.1)
Requires-Dist: pytz (==2020.4)
Requires-Dist: six (==1.15.0)
Requires-Dist: svgwrite (==1.4)
